random_credit_card/__init__.py
random_credit_card/credit_cards.py
random_credit_card-0.1.0.dist-info/LICENSE
random_credit_card-0.1.0.dist-info/METADATA
random_credit_card-0.1.0.dist-info/WHEEL
random_credit_card-0.1.0.dist-info/RECORD
