Metadata-Version: 2.1
Name: random-credit-card
Version: 0.1.0
Summary: Generate random but theoretically valid credit card numbers.
Author: alexandrerbb
Requires-Python: >=3.12,<4.0
Classifier: Programming Language :: Python :: 3
Classifier: Programming Language :: Python :: 3.12
